MANIFEST.in
README.rst
nose_congestion.py
setup.cfg
setup.py
nose_congestion.egg-info/PKG-INFO
nose_congestion.egg-info/SOURCES.txt
nose_congestion.egg-info/dependency_links.txt
nose_congestion.egg-info/entry_points.txt
nose_congestion.egg-info/not-zip-safe
nose_congestion.egg-info/top_level.txt