Metadata-Version: 1.0
Name: nose-congestion
Version: 0.0.3
Summary: Find slow test setUp/tearDown
Home-page: http://github.com/acdha/nose-congestion
Author: Chris Adams
Author-email: chris@improbable.org
License: UNKNOWN
Platform: UNKNOWN
